{
    "nodes": [
        {
            "name": "Adam Sandler",
            "group": 0,
            "count": 370
        },
        {
            "name": "Jake Gyllenhaal",
            "group": 0,
            "count": 17
        },
        {
            "name": "Miley Cyrus",
            "group": 0,
            "count": 293
        },
        {
            "name": "Olivia Wilde",
            "group": 0,
            "count": 310
        },
        {
            "name": "Bradley Cooper",
            "group": 0,
            "count": 1268
        },
        {
            "name": "Bruce Willis",
            "group": 0,
            "count": 2032
        },
        {
            "name": "Carrie Fisher",
            "group": 0,
            "count": 171
        },
        {
            "name": "Chlo\u00eb Grace Moretz",
            "group": 0,
            "count": 1221
        },
        {
            "name": "Amber Heard",
            "group": 0,
            "count": 51
        },
        {
            "name": "Channing Tatum",
            "group": 0,
            "count": 170
        },
        {
            "name": "Robin Wright",
            "group": 0,
            "count": 494
        },
        {
            "name": "Sam Claflin",
            "group": 0,
            "count": 252
        },
        {
            "name": "Natalie Portman",
            "group": 0,
            "count": 776
        },
        {
            "name": "Kim Kardashian",
            "group": 0,
            "count": 191
        },
        {
            "name": "Chuck Norris",
            "group": 0,
            "count": 324
        },
        {
            "name": "Leonardo DiCaprio",
            "group": 0,
            "count": 104
        },
        {
            "name": "Reese Witherspoon",
            "group": 0,
            "count": 224
        },
        {
            "name": "Morena Baccarin",
            "group": 0,
            "count": 109
        },
        {
            "name": "Alexis Bledel",
            "group": 0,
            "count": 70
        },
        {
            "name": "Melissa McCarthy",
            "group": 0,
            "count": 49
        },
        {
            "name": "Jared Leto",
            "group": 0,
            "count": 722
        },
        {
            "name": "Kate Winslet",
            "group": 0,
            "count": 92
        },
        {
            "name": "Anne Hathaway",
            "group": 0,
            "count": 91
        },
        {
            "name": "George Clooney",
            "group": 0,
            "count": 427
        },
        {
            "name": "Megan Fox",
            "group": 0,
            "count": 141
        },
        {
            "name": "Amy Adams",
            "group": 0,
            "count": 186
        },
        {
            "name": "Jennifer Lawrence",
            "group": 0,
            "count": 52
        },
        {
            "name": "Matthew McConaughey",
            "group": 0,
            "count": 180
        },
        {
            "name": "Angelina Jolie",
            "group": 0,
            "count": 163
        },
        {
            "name": "Mayim Bialik",
            "group": 0,
            "count": 136
        },
        {
            "name": "Jennifer Aniston",
            "group": 0,
            "count": 151
        },
        {
            "name": "Emma Stone",
            "group": 0,
            "count": 36
        },
        {
            "name": "Michael Douglas",
            "group": 0,
            "count": 317
        },
        {
            "name": "Blake Lively",
            "group": 0,
            "count": 432
        },
        {
            "name": "Daniel Craig",
            "group": 0,
            "count": 282
        },
        {
            "name": "Bruce Lee",
            "group": 0,
            "count": 45
        },
        {
            "name": "Jim Parsons",
            "group": 0,
            "count": 57
        },
        {
            "name": "Shailene Woodley",
            "group": 0,
            "count": 147
        },
        {
            "name": "Johnny Galecki",
            "group": 0,
            "count": 139
        },
        {
            "name": "Macaulay Culkin",
            "group": 0,
            "count": 623
        },
        {
            "name": "Julianne Moore",
            "group": 0,
            "count": 138
        },
        {
            "name": "Zac Efron",
            "group": 0,
            "count": 125
        },
        {
            "name": "Kristen Stewart",
            "group": 0,
            "count": 576
        },
        {
            "name": "Jeffrey Dean Morgan",
            "group": 0,
            "count": 424
        },
        {
            "name": "Emily Blunt",
            "group": 0,
            "count": 78
        },
        {
            "name": "G\u00f6tz George",
            "group": 0,
            "count": 84
        },
        {
            "name": "Caitlyn Jenner",
            "group": 0,
            "count": 109
        },
        {
            "name": "Charlize Theron",
            "group": 0,
            "count": 186
        },
        {
            "name": "Brad Pitt",
            "group": 0,
            "count": 197
        },
        {
            "name": "John Cena",
            "group": 0,
            "count": 180
        },
        {
            "name": "Josefine Preu\u00df",
            "group": 0,
            "count": 129
        },
        {
            "name": "Anthony Hopkins",
            "group": 0,
            "count": 93
        },
        {
            "name": "Patrick Swayze",
            "group": 0,
            "count": 26
        },
        {
            "name": "Michaela Schaffrath",
            "group": 0,
            "count": 319
        },
        {
            "name": "Emma Roberts",
            "group": 0,
            "count": 136
        },
        {
            "name": "Heidi Klum",
            "group": 0,
            "count": 511
        },
        {
            "name": "James Franco",
            "group": 0,
            "count": 25
        },
        {
            "name": "Julia Roberts",
            "group": 0,
            "count": 166
        },
        {
            "name": "Kaley Cuoco",
            "group": 0,
            "count": 246
        },
        {
            "name": "Clint Eastwood",
            "group": 0,
            "count": 60
        },
        {
            "name": "Ryan Gosling",
            "group": 0,
            "count": 110
        },
        {
            "name": "Ben Affleck",
            "group": 0,
            "count": 270
        },
        {
            "name": "Jack Nicholson",
            "group": 0,
            "count": 109
        },
        {
            "name": "Jennifer Lopez",
            "group": 0,
            "count": 79
        },
        {
            "name": "Morgan Freeman",
            "group": 0,
            "count": 51
        },
        {
            "name": "Ariana Grande",
            "group": 0,
            "count": 39
        },
        {
            "name": "Anton Yelchin",
            "group": 0,
            "count": 97
        },
        {
            "name": "Sandra Bullock",
            "group": 0,
            "count": 442
        },
        {
            "name": "Mila Kunis",
            "group": 0,
            "count": 59
        },
        {
            "name": "Ashton Kutcher",
            "group": 0,
            "count": 104
        },
        {
            "name": "Charlie Sheen",
            "group": 0,
            "count": 188
        },
        {
            "name": "Tina Turner",
            "group": 0,
            "count": 75
        },
        {
            "name": "Kevin Spacey",
            "group": 0,
            "count": 95
        },
        {
            "name": "Alan Rickman",
            "group": 0,
            "count": 19
        },
        {
            "name": "Keanu Reeves",
            "group": 0,
            "count": 16
        },
        {
            "name": "Quentin Tarantino",
            "group": 0,
            "count": 33
        },
        {
            "name": "Samuel L. Jackson",
            "group": 0,
            "count": 20
        },
        {
            "name": "Denzel Washington",
            "group": 0,
            "count": 31
        },
        {
            "name": "Johnny Depp",
            "group": 0,
            "count": 69
        },
        {
            "name": "Cameron Diaz",
            "group": 0,
            "count": 27
        },
        {
            "name": "Paul Walker",
            "group": 0,
            "count": 29
        },
        {
            "name": "Tupac Shakur",
            "group": 0,
            "count": 103
        },
        {
            "name": "Sylvester Stallone",
            "group": 0,
            "count": 88
        },
        {
            "name": "Ruby O. Fee",
            "group": 0,
            "count": 114
        },
        {
            "name": "Selena Gomez",
            "group": 0,
            "count": 101
        },
        {
            "name": "Wentworth Miller",
            "group": 0,
            "count": 63
        },
        {
            "name": "Johnny Cash",
            "group": 0,
            "count": 88
        },
        {
            "name": "Daniel Radcliffe",
            "group": 0,
            "count": 29
        },
        {
            "name": "Kat Dennings",
            "group": 0,
            "count": 55
        },
        {
            "name": "Peter Lustig",
            "group": 0,
            "count": 39
        },
        {
            "name": "Debbie Reynolds",
            "group": 0,
            "count": 28
        },
        {
            "name": "Keira Knightley",
            "group": 0,
            "count": 36
        },
        {
            "name": "Tom Hanks",
            "group": 0,
            "count": 34
        },
        {
            "name": "John Travolta",
            "group": 0,
            "count": 31
        },
        {
            "name": "Mel Gibson",
            "group": 0,
            "count": 46
        },
        {
            "name": "Robin Williams",
            "group": 0,
            "count": 21
        },
        {
            "name": "Priscilla Presley",
            "group": 0,
            "count": 42
        },
        {
            "name": "Heath Ledger",
            "group": 0,
            "count": 13
        },
        {
            "name": "Norman Reedus",
            "group": 0,
            "count": 3
        }
    ],
    "links": [
        {
            "source": 8,
            "target": 7,
            "weight": 6
        },
        {
            "source": 18,
            "target": 19,
            "weight": 1
        },
        {
            "source": 7,
            "target": 21,
            "weight": 1
        },
        {
            "source": 22,
            "target": 4,
            "weight": 3
        },
        {
            "source": 22,
            "target": 3,
            "weight": 6
        },
        {
            "source": 4,
            "target": 3,
            "weight": 5
        },
        {
            "source": 27,
            "target": 12,
            "weight": 3
        },
        {
            "source": 5,
            "target": 43,
            "weight": 7
        },
        {
            "source": 28,
            "target": 48,
            "weight": 36
        },
        {
            "source": 7,
            "target": 39,
            "weight": 12
        },
        {
            "source": 55,
            "target": 56,
            "weight": 1
        },
        {
            "source": 4,
            "target": 39,
            "weight": 5
        },
        {
            "source": 6,
            "target": 53,
            "weight": 1
        },
        {
            "source": 61,
            "target": 11,
            "weight": 1
        },
        {
            "source": 62,
            "target": 32,
            "weight": 2
        },
        {
            "source": 58,
            "target": 42,
            "weight": 3
        },
        {
            "source": 57,
            "target": 42,
            "weight": 1
        },
        {
            "source": 57,
            "target": 12,
            "weight": 1
        },
        {
            "source": 42,
            "target": 12,
            "weight": 10
        },
        {
            "source": 69,
            "target": 68,
            "weight": 8
        },
        {
            "source": 4,
            "target": 5,
            "weight": 24
        },
        {
            "source": 5,
            "target": 10,
            "weight": 7
        },
        {
            "source": 16,
            "target": 60,
            "weight": 2
        },
        {
            "source": 27,
            "target": 41,
            "weight": 4
        },
        {
            "source": 75,
            "target": 76,
            "weight": 4
        },
        {
            "source": 62,
            "target": 10,
            "weight": 1
        },
        {
            "source": 5,
            "target": 12,
            "weight": 22
        },
        {
            "source": 25,
            "target": 16,
            "weight": 1
        },
        {
            "source": 4,
            "target": 15,
            "weight": 5
        },
        {
            "source": 39,
            "target": 3,
            "weight": 1
        },
        {
            "source": 42,
            "target": 16,
            "weight": 2
        },
        {
            "source": 13,
            "target": 2,
            "weight": 1
        },
        {
            "source": 53,
            "target": 41,
            "weight": 2
        },
        {
            "source": 5,
            "target": 20,
            "weight": 16
        },
        {
            "source": 23,
            "target": 12,
            "weight": 2
        },
        {
            "source": 68,
            "target": 83,
            "weight": 3
        },
        {
            "source": 68,
            "target": 67,
            "weight": 1
        },
        {
            "source": 83,
            "target": 67,
            "weight": 1
        },
        {
            "source": 62,
            "target": 20,
            "weight": 3
        },
        {
            "source": 61,
            "target": 23,
            "weight": 11
        },
        {
            "source": 5,
            "target": 14,
            "weight": 8
        },
        {
            "source": 7,
            "target": 40,
            "weight": 3
        },
        {
            "source": 7,
            "target": 42,
            "weight": 5
        },
        {
            "source": 6,
            "target": 11,
            "weight": 2
        },
        {
            "source": 43,
            "target": 24,
            "weight": 2
        },
        {
            "source": 4,
            "target": 7,
            "weight": 17
        },
        {
            "source": 4,
            "target": 12,
            "weight": 11
        },
        {
            "source": 7,
            "target": 12,
            "weight": 8
        },
        {
            "source": 4,
            "target": 14,
            "weight": 10
        },
        {
            "source": 55,
            "target": 63,
            "weight": 7
        },
        {
            "source": 55,
            "target": 24,
            "weight": 3
        },
        {
            "source": 63,
            "target": 24,
            "weight": 3
        },
        {
            "source": 33,
            "target": 7,
            "weight": 3
        },
        {
            "source": 78,
            "target": 60,
            "weight": 1
        },
        {
            "source": 32,
            "target": 12,
            "weight": 5
        },
        {
            "source": 5,
            "target": 23,
            "weight": 7
        },
        {
            "source": 42,
            "target": 10,
            "weight": 3
        },
        {
            "source": 42,
            "target": 41,
            "weight": 2
        },
        {
            "source": 10,
            "target": 41,
            "weight": 1
        },
        {
            "source": 19,
            "target": 67,
            "weight": 5
        },
        {
            "source": 14,
            "target": 20,
            "weight": 3
        },
        {
            "source": 48,
            "target": 41,
            "weight": 2
        },
        {
            "source": 47,
            "target": 15,
            "weight": 4
        },
        {
            "source": 4,
            "target": 62,
            "weight": 3
        },
        {
            "source": 47,
            "target": 44,
            "weight": 2
        },
        {
            "source": 47,
            "target": 23,
            "weight": 7
        },
        {
            "source": 44,
            "target": 23,
            "weight": 2
        },
        {
            "source": 61,
            "target": 5,
            "weight": 4
        },
        {
            "source": 25,
            "target": 33,
            "weight": 2
        },
        {
            "source": 2,
            "target": 83,
            "weight": 1
        },
        {
            "source": 30,
            "target": 15,
            "weight": 2
        },
        {
            "source": 7,
            "target": 60,
            "weight": 1
        },
        {
            "source": 23,
            "target": 30,
            "weight": 2
        },
        {
            "source": 20,
            "target": 30,
            "weight": 1
        },
        {
            "source": 14,
            "target": 38,
            "weight": 1
        },
        {
            "source": 55,
            "target": 10,
            "weight": 2
        },
        {
            "source": 23,
            "target": 92,
            "weight": 1
        },
        {
            "source": 5,
            "target": 7,
            "weight": 15
        },
        {
            "source": 0,
            "target": 14,
            "weight": 1
        },
        {
            "source": 43,
            "target": 10,
            "weight": 1
        },
        {
            "source": 46,
            "target": 3,
            "weight": 1
        },
        {
            "source": 0,
            "target": 22,
            "weight": 6
        },
        {
            "source": 25,
            "target": 30,
            "weight": 1
        },
        {
            "source": 6,
            "target": 12,
            "weight": 1
        },
        {
            "source": 65,
            "target": 7,
            "weight": 1
        },
        {
            "source": 65,
            "target": 39,
            "weight": 3
        },
        {
            "source": 65,
            "target": 12,
            "weight": 1
        },
        {
            "source": 39,
            "target": 12,
            "weight": 5
        },
        {
            "source": 33,
            "target": 3,
            "weight": 3
        },
        {
            "source": 7,
            "target": 59,
            "weight": 1
        },
        {
            "source": 21,
            "target": 16,
            "weight": 5
        },
        {
            "source": 21,
            "target": 67,
            "weight": 4
        },
        {
            "source": 16,
            "target": 67,
            "weight": 5
        },
        {
            "source": 7,
            "target": 20,
            "weight": 13
        },
        {
            "source": 14,
            "target": 60,
            "weight": 2
        },
        {
            "source": 51,
            "target": 70,
            "weight": 1
        },
        {
            "source": 4,
            "target": 27,
            "weight": 4
        },
        {
            "source": 48,
            "target": 21,
            "weight": 3
        },
        {
            "source": 69,
            "target": 61,
            "weight": 1
        },
        {
            "source": 26,
            "target": 42,
            "weight": 5
        },
        {
            "source": 70,
            "target": 3,
            "weight": 2
        },
        {
            "source": 61,
            "target": 50,
            "weight": 6
        },
        {
            "source": 5,
            "target": 42,
            "weight": 2
        },
        {
            "source": 4,
            "target": 55,
            "weight": 4
        },
        {
            "source": 4,
            "target": 23,
            "weight": 4
        },
        {
            "source": 4,
            "target": 43,
            "weight": 7
        },
        {
            "source": 23,
            "target": 43,
            "weight": 2
        },
        {
            "source": 6,
            "target": 10,
            "weight": 2
        },
        {
            "source": 33,
            "target": 53,
            "weight": 2
        },
        {
            "source": 23,
            "target": 26,
            "weight": 1
        },
        {
            "source": 14,
            "target": 43,
            "weight": 1
        },
        {
            "source": 44,
            "target": 12,
            "weight": 6
        },
        {
            "source": 44,
            "target": 37,
            "weight": 1
        },
        {
            "source": 12,
            "target": 37,
            "weight": 2
        },
        {
            "source": 13,
            "target": 42,
            "weight": 3
        },
        {
            "source": 57,
            "target": 80,
            "weight": 3
        },
        {
            "source": 55,
            "target": 93,
            "weight": 4
        },
        {
            "source": 48,
            "target": 15,
            "weight": 5
        },
        {
            "source": 42,
            "target": 2,
            "weight": 2
        },
        {
            "source": 20,
            "target": 12,
            "weight": 13
        },
        {
            "source": 7,
            "target": 62,
            "weight": 2
        },
        {
            "source": 50,
            "target": 12,
            "weight": 1
        },
        {
            "source": 35,
            "target": 5,
            "weight": 1
        },
        {
            "source": 0,
            "target": 34,
            "weight": 2
        },
        {
            "source": 4,
            "target": 58,
            "weight": 3
        },
        {
            "source": 47,
            "target": 84,
            "weight": 3
        },
        {
            "source": 20,
            "target": 32,
            "weight": 3
        },
        {
            "source": 6,
            "target": 67,
            "weight": 1
        },
        {
            "source": 40,
            "target": 3,
            "weight": 3
        },
        {
            "source": 35,
            "target": 12,
            "weight": 4
        },
        {
            "source": 33,
            "target": 57,
            "weight": 1
        },
        {
            "source": 61,
            "target": 26,
            "weight": 2
        },
        {
            "source": 61,
            "target": 10,
            "weight": 2
        },
        {
            "source": 26,
            "target": 10,
            "weight": 3
        },
        {
            "source": 55,
            "target": 67,
            "weight": 3
        },
        {
            "source": 6,
            "target": 16,
            "weight": 1
        },
        {
            "source": 33,
            "target": 42,
            "weight": 2
        },
        {
            "source": 30,
            "target": 38,
            "weight": 5
        },
        {
            "source": 7,
            "target": 2,
            "weight": 3
        },
        {
            "source": 5,
            "target": 3,
            "weight": 3
        },
        {
            "source": 20,
            "target": 86,
            "weight": 4
        },
        {
            "source": 23,
            "target": 10,
            "weight": 1
        },
        {
            "source": 61,
            "target": 4,
            "weight": 2
        },
        {
            "source": 53,
            "target": 16,
            "weight": 2
        },
        {
            "source": 55,
            "target": 36,
            "weight": 1
        },
        {
            "source": 2,
            "target": 16,
            "weight": 1
        },
        {
            "source": 22,
            "target": 61,
            "weight": 1
        },
        {
            "source": 18,
            "target": 6,
            "weight": 1
        },
        {
            "source": 23,
            "target": 67,
            "weight": 16
        },
        {
            "source": 33,
            "target": 37,
            "weight": 3
        },
        {
            "source": 91,
            "target": 68,
            "weight": 3
        },
        {
            "source": 5,
            "target": 32,
            "weight": 8
        },
        {
            "source": 43,
            "target": 72,
            "weight": 3
        },
        {
            "source": 50,
            "target": 32,
            "weight": 1
        },
        {
            "source": 32,
            "target": 67,
            "weight": 3
        },
        {
            "source": 7,
            "target": 16,
            "weight": 3
        },
        {
            "source": 33,
            "target": 12,
            "weight": 6
        },
        {
            "source": 34,
            "target": 43,
            "weight": 2
        },
        {
            "source": 27,
            "target": 16,
            "weight": 1
        },
        {
            "source": 6,
            "target": 39,
            "weight": 3
        },
        {
            "source": 47,
            "target": 2,
            "weight": 1
        },
        {
            "source": 44,
            "target": 36,
            "weight": 1
        },
        {
            "source": 44,
            "target": 2,
            "weight": 1
        },
        {
            "source": 36,
            "target": 2,
            "weight": 2
        },
        {
            "source": 5,
            "target": 91,
            "weight": 1
        },
        {
            "source": 87,
            "target": 63,
            "weight": 1
        },
        {
            "source": 11,
            "target": 67,
            "weight": 4
        },
        {
            "source": 9,
            "target": 24,
            "weight": 1
        },
        {
            "source": 25,
            "target": 37,
            "weight": 2
        },
        {
            "source": 28,
            "target": 6,
            "weight": 1
        },
        {
            "source": 33,
            "target": 29,
            "weight": 4
        },
        {
            "source": 4,
            "target": 50,
            "weight": 1
        },
        {
            "source": 87,
            "target": 38,
            "weight": 1
        },
        {
            "source": 38,
            "target": 12,
            "weight": 2
        },
        {
            "source": 39,
            "target": 2,
            "weight": 1
        },
        {
            "source": 39,
            "target": 11,
            "weight": 3
        },
        {
            "source": 2,
            "target": 11,
            "weight": 2
        },
        {
            "source": 4,
            "target": 26,
            "weight": 3
        },
        {
            "source": 5,
            "target": 21,
            "weight": 3
        },
        {
            "source": 33,
            "target": 4,
            "weight": 10
        },
        {
            "source": 36,
            "target": 60,
            "weight": 1
        },
        {
            "source": 9,
            "target": 27,
            "weight": 2
        },
        {
            "source": 69,
            "target": 4,
            "weight": 3
        },
        {
            "source": 7,
            "target": 43,
            "weight": 4
        },
        {
            "source": 33,
            "target": 82,
            "weight": 1
        },
        {
            "source": 4,
            "target": 20,
            "weight": 23
        },
        {
            "source": 5,
            "target": 95,
            "weight": 1
        },
        {
            "source": 42,
            "target": 67,
            "weight": 2
        },
        {
            "source": 68,
            "target": 12,
            "weight": 1
        },
        {
            "source": 53,
            "target": 10,
            "weight": 2
        },
        {
            "source": 5,
            "target": 55,
            "weight": 2
        },
        {
            "source": 4,
            "target": 35,
            "weight": 1
        },
        {
            "source": 58,
            "target": 3,
            "weight": 2
        },
        {
            "source": 25,
            "target": 34,
            "weight": 1
        },
        {
            "source": 5,
            "target": 79,
            "weight": 1
        },
        {
            "source": 5,
            "target": 92,
            "weight": 1
        },
        {
            "source": 79,
            "target": 92,
            "weight": 1
        },
        {
            "source": 7,
            "target": 86,
            "weight": 2
        },
        {
            "source": 4,
            "target": 57,
            "weight": 6
        },
        {
            "source": 44,
            "target": 55,
            "weight": 2
        },
        {
            "source": 55,
            "target": 12,
            "weight": 7
        },
        {
            "source": 61,
            "target": 42,
            "weight": 2
        },
        {
            "source": 3,
            "target": 60,
            "weight": 1
        },
        {
            "source": 30,
            "target": 19,
            "weight": 1
        },
        {
            "source": 30,
            "target": 37,
            "weight": 2
        },
        {
            "source": 19,
            "target": 37,
            "weight": 2
        },
        {
            "source": 65,
            "target": 3,
            "weight": 2
        },
        {
            "source": 14,
            "target": 23,
            "weight": 1
        },
        {
            "source": 24,
            "target": 11,
            "weight": 1
        },
        {
            "source": 5,
            "target": 16,
            "weight": 2
        },
        {
            "source": 66,
            "target": 4,
            "weight": 3
        },
        {
            "source": 66,
            "target": 67,
            "weight": 6
        },
        {
            "source": 4,
            "target": 67,
            "weight": 2
        },
        {
            "source": 4,
            "target": 44,
            "weight": 1
        },
        {
            "source": 70,
            "target": 2,
            "weight": 4
        },
        {
            "source": 55,
            "target": 37,
            "weight": 2
        },
        {
            "source": 18,
            "target": 15,
            "weight": 2
        },
        {
            "source": 20,
            "target": 38,
            "weight": 2
        },
        {
            "source": 4,
            "target": 9,
            "weight": 4
        },
        {
            "source": 4,
            "target": 36,
            "weight": 1
        },
        {
            "source": 9,
            "target": 36,
            "weight": 1
        },
        {
            "source": 7,
            "target": 23,
            "weight": 1
        },
        {
            "source": 69,
            "target": 10,
            "weight": 2
        },
        {
            "source": 51,
            "target": 5,
            "weight": 1
        },
        {
            "source": 7,
            "target": 32,
            "weight": 5
        },
        {
            "source": 16,
            "target": 10,
            "weight": 1
        },
        {
            "source": 16,
            "target": 11,
            "weight": 1
        },
        {
            "source": 0,
            "target": 23,
            "weight": 1
        },
        {
            "source": 47,
            "target": 58,
            "weight": 1
        },
        {
            "source": 23,
            "target": 58,
            "weight": 1
        },
        {
            "source": 33,
            "target": 44,
            "weight": 1
        },
        {
            "source": 21,
            "target": 72,
            "weight": 1
        },
        {
            "source": 5,
            "target": 46,
            "weight": 1
        },
        {
            "source": 4,
            "target": 2,
            "weight": 4
        },
        {
            "source": 7,
            "target": 3,
            "weight": 1
        },
        {
            "source": 5,
            "target": 67,
            "weight": 1
        },
        {
            "source": 20,
            "target": 39,
            "weight": 3
        },
        {
            "source": 11,
            "target": 37,
            "weight": 1
        },
        {
            "source": 57,
            "target": 67,
            "weight": 1
        },
        {
            "source": 48,
            "target": 78,
            "weight": 2
        },
        {
            "source": 69,
            "target": 70,
            "weight": 3
        },
        {
            "source": 5,
            "target": 9,
            "weight": 1
        },
        {
            "source": 69,
            "target": 7,
            "weight": 3
        },
        {
            "source": 44,
            "target": 24,
            "weight": 1
        },
        {
            "source": 21,
            "target": 53,
            "weight": 1
        },
        {
            "source": 20,
            "target": 2,
            "weight": 2
        },
        {
            "source": 20,
            "target": 84,
            "weight": 1
        },
        {
            "source": 2,
            "target": 84,
            "weight": 2
        },
        {
            "source": 12,
            "target": 83,
            "weight": 2
        },
        {
            "source": 5,
            "target": 34,
            "weight": 7
        },
        {
            "source": 48,
            "target": 19,
            "weight": 3
        },
        {
            "source": 4,
            "target": 38,
            "weight": 3
        },
        {
            "source": 54,
            "target": 30,
            "weight": 6
        },
        {
            "source": 78,
            "target": 32,
            "weight": 2
        },
        {
            "source": 0,
            "target": 5,
            "weight": 4
        },
        {
            "source": 42,
            "target": 84,
            "weight": 1
        },
        {
            "source": 43,
            "target": 37,
            "weight": 2
        },
        {
            "source": 4,
            "target": 71,
            "weight": 1
        },
        {
            "source": 3,
            "target": 71,
            "weight": 1
        },
        {
            "source": 33,
            "target": 48,
            "weight": 1
        },
        {
            "source": 39,
            "target": 67,
            "weight": 4
        },
        {
            "source": 33,
            "target": 80,
            "weight": 1
        },
        {
            "source": 65,
            "target": 4,
            "weight": 2
        },
        {
            "source": 14,
            "target": 96,
            "weight": 1
        },
        {
            "source": 47,
            "target": 91,
            "weight": 1
        },
        {
            "source": 91,
            "target": 15,
            "weight": 1
        },
        {
            "source": 14,
            "target": 3,
            "weight": 1
        },
        {
            "source": 9,
            "target": 30,
            "weight": 1
        },
        {
            "source": 28,
            "target": 12,
            "weight": 4
        },
        {
            "source": 48,
            "target": 12,
            "weight": 2
        },
        {
            "source": 54,
            "target": 67,
            "weight": 1
        },
        {
            "source": 2,
            "target": 12,
            "weight": 1
        },
        {
            "source": 5,
            "target": 40,
            "weight": 1
        },
        {
            "source": 20,
            "target": 43,
            "weight": 2
        },
        {
            "source": 43,
            "target": 12,
            "weight": 6
        },
        {
            "source": 38,
            "target": 40,
            "weight": 1
        },
        {
            "source": 69,
            "target": 60,
            "weight": 1
        },
        {
            "source": 0,
            "target": 4,
            "weight": 3
        },
        {
            "source": 5,
            "target": 70,
            "weight": 2
        },
        {
            "source": 33,
            "target": 10,
            "weight": 4
        },
        {
            "source": 10,
            "target": 37,
            "weight": 1
        },
        {
            "source": 58,
            "target": 53,
            "weight": 2
        },
        {
            "source": 5,
            "target": 11,
            "weight": 3
        },
        {
            "source": 4,
            "target": 32,
            "weight": 5
        },
        {
            "source": 54,
            "target": 88,
            "weight": 3
        },
        {
            "source": 42,
            "target": 24,
            "weight": 2
        },
        {
            "source": 47,
            "target": 12,
            "weight": 2
        },
        {
            "source": 9,
            "target": 39,
            "weight": 2
        },
        {
            "source": 16,
            "target": 85,
            "weight": 1
        },
        {
            "source": 46,
            "target": 7,
            "weight": 1
        },
        {
            "source": 36,
            "target": 12,
            "weight": 1
        },
        {
            "source": 53,
            "target": 37,
            "weight": 1
        },
        {
            "source": 58,
            "target": 12,
            "weight": 3
        },
        {
            "source": 6,
            "target": 40,
            "weight": 1
        },
        {
            "source": 14,
            "target": 39,
            "weight": 1
        },
        {
            "source": 46,
            "target": 67,
            "weight": 1
        },
        {
            "source": 24,
            "target": 12,
            "weight": 4
        },
        {
            "source": 54,
            "target": 50,
            "weight": 3
        },
        {
            "source": 55,
            "target": 53,
            "weight": 3
        },
        {
            "source": 12,
            "target": 67,
            "weight": 1
        },
        {
            "source": 7,
            "target": 10,
            "weight": 5
        },
        {
            "source": 25,
            "target": 54,
            "weight": 3
        },
        {
            "source": 66,
            "target": 16,
            "weight": 2
        },
        {
            "source": 53,
            "target": 3,
            "weight": 1
        },
        {
            "source": 55,
            "target": 96,
            "weight": 1
        },
        {
            "source": 12,
            "target": 96,
            "weight": 1
        },
        {
            "source": 39,
            "target": 10,
            "weight": 2
        },
        {
            "source": 23,
            "target": 11,
            "weight": 5
        },
        {
            "source": 78,
            "target": 10,
            "weight": 2
        },
        {
            "source": 69,
            "target": 48,
            "weight": 1
        },
        {
            "source": 48,
            "target": 10,
            "weight": 3
        },
        {
            "source": 36,
            "target": 38,
            "weight": 5
        },
        {
            "source": 36,
            "target": 58,
            "weight": 3
        },
        {
            "source": 38,
            "target": 58,
            "weight": 3
        },
        {
            "source": 1,
            "target": 15,
            "weight": 1
        },
        {
            "source": 48,
            "target": 92,
            "weight": 1
        },
        {
            "source": 22,
            "target": 42,
            "weight": 1
        },
        {
            "source": 7,
            "target": 67,
            "weight": 1
        },
        {
            "source": 18,
            "target": 3,
            "weight": 1
        },
        {
            "source": 50,
            "target": 83,
            "weight": 6
        },
        {
            "source": 33,
            "target": 85,
            "weight": 2
        },
        {
            "source": 58,
            "target": 39,
            "weight": 5
        },
        {
            "source": 20,
            "target": 10,
            "weight": 1
        },
        {
            "source": 55,
            "target": 50,
            "weight": 1
        },
        {
            "source": 35,
            "target": 86,
            "weight": 2
        },
        {
            "source": 4,
            "target": 10,
            "weight": 13
        },
        {
            "source": 5,
            "target": 6,
            "weight": 1
        },
        {
            "source": 55,
            "target": 83,
            "weight": 1
        },
        {
            "source": 5,
            "target": 39,
            "weight": 7
        },
        {
            "source": 8,
            "target": 13,
            "weight": 1
        },
        {
            "source": 29,
            "target": 10,
            "weight": 1
        },
        {
            "source": 5,
            "target": 64,
            "weight": 1
        },
        {
            "source": 54,
            "target": 31,
            "weight": 2
        },
        {
            "source": 54,
            "target": 26,
            "weight": 1
        },
        {
            "source": 31,
            "target": 26,
            "weight": 1
        },
        {
            "source": 31,
            "target": 88,
            "weight": 5
        },
        {
            "source": 26,
            "target": 88,
            "weight": 1
        },
        {
            "source": 23,
            "target": 53,
            "weight": 1
        },
        {
            "source": 53,
            "target": 67,
            "weight": 1
        },
        {
            "source": 69,
            "target": 41,
            "weight": 1
        },
        {
            "source": 4,
            "target": 41,
            "weight": 3
        },
        {
            "source": 13,
            "target": 84,
            "weight": 1
        },
        {
            "source": 12,
            "target": 3,
            "weight": 2
        },
        {
            "source": 7,
            "target": 13,
            "weight": 1
        },
        {
            "source": 33,
            "target": 58,
            "weight": 1
        },
        {
            "source": 46,
            "target": 16,
            "weight": 1
        },
        {
            "source": 27,
            "target": 53,
            "weight": 1
        },
        {
            "source": 62,
            "target": 15,
            "weight": 3
        },
        {
            "source": 13,
            "target": 12,
            "weight": 2
        },
        {
            "source": 68,
            "target": 16,
            "weight": 1
        },
        {
            "source": 22,
            "target": 13,
            "weight": 1
        },
        {
            "source": 22,
            "target": 16,
            "weight": 1
        },
        {
            "source": 13,
            "target": 16,
            "weight": 1
        },
        {
            "source": 15,
            "target": 60,
            "weight": 3
        },
        {
            "source": 15,
            "target": 41,
            "weight": 3
        },
        {
            "source": 60,
            "target": 41,
            "weight": 5
        },
        {
            "source": 0,
            "target": 3,
            "weight": 3
        },
        {
            "source": 53,
            "target": 17,
            "weight": 3
        },
        {
            "source": 6,
            "target": 14,
            "weight": 1
        },
        {
            "source": 38,
            "target": 39,
            "weight": 1
        },
        {
            "source": 69,
            "target": 30,
            "weight": 4
        },
        {
            "source": 28,
            "target": 16,
            "weight": 2
        },
        {
            "source": 5,
            "target": 30,
            "weight": 2
        },
        {
            "source": 4,
            "target": 64,
            "weight": 2
        },
        {
            "source": 54,
            "target": 57,
            "weight": 2
        },
        {
            "source": 48,
            "target": 59,
            "weight": 3
        },
        {
            "source": 7,
            "target": 88,
            "weight": 1
        },
        {
            "source": 5,
            "target": 44,
            "weight": 1
        },
        {
            "source": 7,
            "target": 93,
            "weight": 1
        },
        {
            "source": 43,
            "target": 86,
            "weight": 1
        },
        {
            "source": 86,
            "target": 12,
            "weight": 1
        },
        {
            "source": 48,
            "target": 38,
            "weight": 1
        },
        {
            "source": 38,
            "target": 41,
            "weight": 1
        },
        {
            "source": 4,
            "target": 70,
            "weight": 1
        },
        {
            "source": 18,
            "target": 23,
            "weight": 1
        },
        {
            "source": 0,
            "target": 72,
            "weight": 1
        },
        {
            "source": 4,
            "target": 72,
            "weight": 1
        },
        {
            "source": 54,
            "target": 39,
            "weight": 1
        },
        {
            "source": 8,
            "target": 33,
            "weight": 1
        },
        {
            "source": 8,
            "target": 40,
            "weight": 1
        },
        {
            "source": 33,
            "target": 40,
            "weight": 2
        },
        {
            "source": 8,
            "target": 48,
            "weight": 1
        },
        {
            "source": 8,
            "target": 47,
            "weight": 2
        },
        {
            "source": 8,
            "target": 23,
            "weight": 3
        },
        {
            "source": 8,
            "target": 67,
            "weight": 2
        },
        {
            "source": 48,
            "target": 47,
            "weight": 2
        },
        {
            "source": 48,
            "target": 23,
            "weight": 2
        },
        {
            "source": 48,
            "target": 67,
            "weight": 1
        },
        {
            "source": 47,
            "target": 67,
            "weight": 2
        },
        {
            "source": 80,
            "target": 10,
            "weight": 1
        },
        {
            "source": 4,
            "target": 11,
            "weight": 3
        },
        {
            "source": 11,
            "target": 41,
            "weight": 2
        },
        {
            "source": 13,
            "target": 67,
            "weight": 1
        },
        {
            "source": 24,
            "target": 17,
            "weight": 2
        },
        {
            "source": 33,
            "target": 30,
            "weight": 1
        },
        {
            "source": 7,
            "target": 83,
            "weight": 3
        },
        {
            "source": 20,
            "target": 42,
            "weight": 2
        },
        {
            "source": 8,
            "target": 78,
            "weight": 2
        },
        {
            "source": 4,
            "target": 42,
            "weight": 4
        },
        {
            "source": 14,
            "target": 32,
            "weight": 1
        },
        {
            "source": 23,
            "target": 20,
            "weight": 3
        },
        {
            "source": 23,
            "target": 32,
            "weight": 1
        },
        {
            "source": 0,
            "target": 39,
            "weight": 1
        },
        {
            "source": 5,
            "target": 29,
            "weight": 1
        },
        {
            "source": 40,
            "target": 10,
            "weight": 1
        },
        {
            "source": 70,
            "target": 55,
            "weight": 1
        },
        {
            "source": 24,
            "target": 67,
            "weight": 1
        },
        {
            "source": 5,
            "target": 82,
            "weight": 2
        },
        {
            "source": 20,
            "target": 3,
            "weight": 1
        },
        {
            "source": 38,
            "target": 83,
            "weight": 1
        },
        {
            "source": 47,
            "target": 55,
            "weight": 3
        },
        {
            "source": 6,
            "target": 37,
            "weight": 2
        },
        {
            "source": 5,
            "target": 54,
            "weight": 1
        },
        {
            "source": 87,
            "target": 42,
            "weight": 1
        },
        {
            "source": 23,
            "target": 21,
            "weight": 1
        },
        {
            "source": 33,
            "target": 38,
            "weight": 1
        },
        {
            "source": 39,
            "target": 16,
            "weight": 1
        },
        {
            "source": 23,
            "target": 42,
            "weight": 3
        },
        {
            "source": 6,
            "target": 83,
            "weight": 1
        },
        {
            "source": 12,
            "target": 41,
            "weight": 1
        },
        {
            "source": 54,
            "target": 91,
            "weight": 1
        },
        {
            "source": 31,
            "target": 91,
            "weight": 1
        },
        {
            "source": 25,
            "target": 4,
            "weight": 1
        },
        {
            "source": 55,
            "target": 88,
            "weight": 3
        },
        {
            "source": 66,
            "target": 17,
            "weight": 1
        },
        {
            "source": 47,
            "target": 3,
            "weight": 1
        },
        {
            "source": 23,
            "target": 3,
            "weight": 1
        },
        {
            "source": 48,
            "target": 5,
            "weight": 1
        },
        {
            "source": 28,
            "target": 55,
            "weight": 4
        },
        {
            "source": 28,
            "target": 63,
            "weight": 1
        },
        {
            "source": 66,
            "target": 42,
            "weight": 1
        },
        {
            "source": 39,
            "target": 32,
            "weight": 2
        },
        {
            "source": 6,
            "target": 7,
            "weight": 3
        },
        {
            "source": 46,
            "target": 70,
            "weight": 2
        },
        {
            "source": 46,
            "target": 85,
            "weight": 2
        },
        {
            "source": 70,
            "target": 85,
            "weight": 2
        },
        {
            "source": 7,
            "target": 44,
            "weight": 2
        },
        {
            "source": 61,
            "target": 12,
            "weight": 2
        },
        {
            "source": 7,
            "target": 58,
            "weight": 4
        },
        {
            "source": 0,
            "target": 20,
            "weight": 2
        },
        {
            "source": 33,
            "target": 39,
            "weight": 1
        },
        {
            "source": 43,
            "target": 21,
            "weight": 1
        },
        {
            "source": 22,
            "target": 2,
            "weight": 1
        },
        {
            "source": 7,
            "target": 14,
            "weight": 1
        },
        {
            "source": 69,
            "target": 12,
            "weight": 1
        },
        {
            "source": 79,
            "target": 67,
            "weight": 1
        },
        {
            "source": 22,
            "target": 44,
            "weight": 1
        },
        {
            "source": 22,
            "target": 12,
            "weight": 1
        },
        {
            "source": 18,
            "target": 26,
            "weight": 1
        },
        {
            "source": 70,
            "target": 30,
            "weight": 3
        },
        {
            "source": 30,
            "target": 42,
            "weight": 1
        },
        {
            "source": 57,
            "target": 27,
            "weight": 1
        },
        {
            "source": 91,
            "target": 83,
            "weight": 2
        },
        {
            "source": 48,
            "target": 27,
            "weight": 1
        },
        {
            "source": 5,
            "target": 50,
            "weight": 1
        },
        {
            "source": 5,
            "target": 83,
            "weight": 2
        },
        {
            "source": 28,
            "target": 33,
            "weight": 1
        },
        {
            "source": 7,
            "target": 91,
            "weight": 4
        },
        {
            "source": 79,
            "target": 7,
            "weight": 2
        },
        {
            "source": 88,
            "target": 2,
            "weight": 1
        },
        {
            "source": 40,
            "target": 39,
            "weight": 1
        },
        {
            "source": 50,
            "target": 53,
            "weight": 1
        },
        {
            "source": 5,
            "target": 72,
            "weight": 1
        },
        {
            "source": 72,
            "target": 39,
            "weight": 1
        },
        {
            "source": 30,
            "target": 12,
            "weight": 1
        },
        {
            "source": 0,
            "target": 41,
            "weight": 1
        },
        {
            "source": 55,
            "target": 57,
            "weight": 1
        },
        {
            "source": 70,
            "target": 21,
            "weight": 2
        },
        {
            "source": 25,
            "target": 79,
            "weight": 1
        },
        {
            "source": 9,
            "target": 12,
            "weight": 2
        },
        {
            "source": 42,
            "target": 32,
            "weight": 1
        },
        {
            "source": 45,
            "target": 10,
            "weight": 1
        },
        {
            "source": 88,
            "target": 37,
            "weight": 1
        },
        {
            "source": 12,
            "target": 16,
            "weight": 1
        },
        {
            "source": 12,
            "target": 10,
            "weight": 3
        },
        {
            "source": 78,
            "target": 3,
            "weight": 1
        },
        {
            "source": 7,
            "target": 84,
            "weight": 2
        },
        {
            "source": 58,
            "target": 24,
            "weight": 1
        },
        {
            "source": 51,
            "target": 42,
            "weight": 1
        },
        {
            "source": 33,
            "target": 32,
            "weight": 1
        },
        {
            "source": 5,
            "target": 17,
            "weight": 1
        },
        {
            "source": 55,
            "target": 20,
            "weight": 1
        },
        {
            "source": 5,
            "target": 13,
            "weight": 2
        },
        {
            "source": 50,
            "target": 42,
            "weight": 1
        },
        {
            "source": 25,
            "target": 42,
            "weight": 1
        },
        {
            "source": 25,
            "target": 41,
            "weight": 1
        },
        {
            "source": 44,
            "target": 88,
            "weight": 2
        },
        {
            "source": 33,
            "target": 59,
            "weight": 2
        },
        {
            "source": 61,
            "target": 20,
            "weight": 1
        },
        {
            "source": 61,
            "target": 32,
            "weight": 2
        },
        {
            "source": 61,
            "target": 76,
            "weight": 2
        },
        {
            "source": 32,
            "target": 76,
            "weight": 3
        },
        {
            "source": 83,
            "target": 84,
            "weight": 2
        },
        {
            "source": 30,
            "target": 21,
            "weight": 1
        },
        {
            "source": 20,
            "target": 29,
            "weight": 2
        },
        {
            "source": 55,
            "target": 92,
            "weight": 1
        },
        {
            "source": 25,
            "target": 9,
            "weight": 2
        },
        {
            "source": 51,
            "target": 62,
            "weight": 1
        },
        {
            "source": 63,
            "target": 10,
            "weight": 1
        },
        {
            "source": 14,
            "target": 55,
            "weight": 2
        },
        {
            "source": 55,
            "target": 29,
            "weight": 3
        },
        {
            "source": 29,
            "target": 12,
            "weight": 3
        },
        {
            "source": 23,
            "target": 55,
            "weight": 4
        },
        {
            "source": 56,
            "target": 11,
            "weight": 2
        },
        {
            "source": 4,
            "target": 21,
            "weight": 1
        },
        {
            "source": 46,
            "target": 43,
            "weight": 1
        },
        {
            "source": 65,
            "target": 55,
            "weight": 2
        },
        {
            "source": 28,
            "target": 42,
            "weight": 1
        },
        {
            "source": 28,
            "target": 39,
            "weight": 1
        },
        {
            "source": 42,
            "target": 39,
            "weight": 1
        },
        {
            "source": 35,
            "target": 71,
            "weight": 1
        },
        {
            "source": 15,
            "target": 10,
            "weight": 1
        },
        {
            "source": 34,
            "target": 24,
            "weight": 1
        },
        {
            "source": 33,
            "target": 55,
            "weight": 1
        },
        {
            "source": 62,
            "target": 39,
            "weight": 1
        },
        {
            "source": 42,
            "target": 3,
            "weight": 2
        },
        {
            "source": 33,
            "target": 20,
            "weight": 1
        },
        {
            "source": 30,
            "target": 58,
            "weight": 1
        },
        {
            "source": 58,
            "target": 37,
            "weight": 1
        },
        {
            "source": 72,
            "target": 27,
            "weight": 1
        },
        {
            "source": 46,
            "target": 12,
            "weight": 2
        },
        {
            "source": 93,
            "target": 2,
            "weight": 2
        },
        {
            "source": 5,
            "target": 71,
            "weight": 1
        },
        {
            "source": 66,
            "target": 7,
            "weight": 1
        },
        {
            "source": 8,
            "target": 30,
            "weight": 1
        },
        {
            "source": 8,
            "target": 42,
            "weight": 2
        },
        {
            "source": 8,
            "target": 2,
            "weight": 1
        },
        {
            "source": 51,
            "target": 12,
            "weight": 1
        },
        {
            "source": 0,
            "target": 9,
            "weight": 1
        },
        {
            "source": 54,
            "target": 55,
            "weight": 2
        },
        {
            "source": 39,
            "target": 53,
            "weight": 1
        },
        {
            "source": 66,
            "target": 43,
            "weight": 1
        },
        {
            "source": 93,
            "target": 32,
            "weight": 1
        },
        {
            "source": 69,
            "target": 14,
            "weight": 1
        },
        {
            "source": 60,
            "target": 67,
            "weight": 1
        },
        {
            "source": 4,
            "target": 30,
            "weight": 1
        },
        {
            "source": 55,
            "target": 43,
            "weight": 2
        },
        {
            "source": 4,
            "target": 89,
            "weight": 1
        },
        {
            "source": 47,
            "target": 38,
            "weight": 1
        },
        {
            "source": 5,
            "target": 60,
            "weight": 1
        },
        {
            "source": 20,
            "target": 19,
            "weight": 2
        },
        {
            "source": 59,
            "target": 78,
            "weight": 1
        },
        {
            "source": 59,
            "target": 32,
            "weight": 2
        },
        {
            "source": 7,
            "target": 55,
            "weight": 2
        },
        {
            "source": 44,
            "target": 16,
            "weight": 1
        },
        {
            "source": 69,
            "target": 13,
            "weight": 1
        },
        {
            "source": 75,
            "target": 16,
            "weight": 1
        },
        {
            "source": 17,
            "target": 16,
            "weight": 1
        },
        {
            "source": 14,
            "target": 15,
            "weight": 1
        },
        {
            "source": 9,
            "target": 67,
            "weight": 1
        },
        {
            "source": 13,
            "target": 81,
            "weight": 1
        },
        {
            "source": 25,
            "target": 77,
            "weight": 1
        },
        {
            "source": 61,
            "target": 33,
            "weight": 2
        },
        {
            "source": 35,
            "target": 14,
            "weight": 1
        },
        {
            "source": 69,
            "target": 42,
            "weight": 2
        },
        {
            "source": 44,
            "target": 29,
            "weight": 1
        },
        {
            "source": 47,
            "target": 45,
            "weight": 1
        },
        {
            "source": 61,
            "target": 49,
            "weight": 1
        },
        {
            "source": 12,
            "target": 52,
            "weight": 1
        },
        {
            "source": 28,
            "target": 7,
            "weight": 1
        },
        {
            "source": 42,
            "target": 15,
            "weight": 1
        },
        {
            "source": 8,
            "target": 12,
            "weight": 1
        },
        {
            "source": 58,
            "target": 72,
            "weight": 1
        },
        {
            "source": 6,
            "target": 70,
            "weight": 1
        },
        {
            "source": 61,
            "target": 62,
            "weight": 1
        },
        {
            "source": 33,
            "target": 62,
            "weight": 1
        },
        {
            "source": 23,
            "target": 78,
            "weight": 1
        },
        {
            "source": 54,
            "target": 40,
            "weight": 1
        },
        {
            "source": 20,
            "target": 41,
            "weight": 1
        },
        {
            "source": 96,
            "target": 67,
            "weight": 1
        },
        {
            "source": 58,
            "target": 13,
            "weight": 1
        },
        {
            "source": 18,
            "target": 20,
            "weight": 1
        },
        {
            "source": 4,
            "target": 56,
            "weight": 1
        },
        {
            "source": 43,
            "target": 52,
            "weight": 1
        },
        {
            "source": 28,
            "target": 61,
            "weight": 1
        },
        {
            "source": 61,
            "target": 48,
            "weight": 1
        },
        {
            "source": 87,
            "target": 32,
            "weight": 1
        },
        {
            "source": 87,
            "target": 12,
            "weight": 1
        },
        {
            "source": 87,
            "target": 76,
            "weight": 1
        },
        {
            "source": 12,
            "target": 76,
            "weight": 2
        },
        {
            "source": 46,
            "target": 55,
            "weight": 1
        },
        {
            "source": 46,
            "target": 78,
            "weight": 1
        },
        {
            "source": 55,
            "target": 78,
            "weight": 1
        },
        {
            "source": 48,
            "target": 4,
            "weight": 1
        },
        {
            "source": 47,
            "target": 40,
            "weight": 1
        },
        {
            "source": 55,
            "target": 40,
            "weight": 1
        },
        {
            "source": 42,
            "target": 11,
            "weight": 2
        },
        {
            "source": 61,
            "target": 83,
            "weight": 1
        },
        {
            "source": 0,
            "target": 53,
            "weight": 1
        },
        {
            "source": 6,
            "target": 23,
            "weight": 1
        },
        {
            "source": 22,
            "target": 27,
            "weight": 1
        },
        {
            "source": 4,
            "target": 6,
            "weight": 1
        },
        {
            "source": 8,
            "target": 5,
            "weight": 1
        },
        {
            "source": 87,
            "target": 80,
            "weight": 1
        },
        {
            "source": 62,
            "target": 11,
            "weight": 1
        },
        {
            "source": 7,
            "target": 38,
            "weight": 2
        },
        {
            "source": 6,
            "target": 54,
            "weight": 1
        },
        {
            "source": 54,
            "target": 37,
            "weight": 1
        },
        {
            "source": 5,
            "target": 62,
            "weight": 2
        },
        {
            "source": 62,
            "target": 12,
            "weight": 2
        },
        {
            "source": 20,
            "target": 80,
            "weight": 1
        },
        {
            "source": 0,
            "target": 7,
            "weight": 1
        },
        {
            "source": 20,
            "target": 60,
            "weight": 1
        },
        {
            "source": 5,
            "target": 86,
            "weight": 1
        },
        {
            "source": 25,
            "target": 39,
            "weight": 1
        },
        {
            "source": 57,
            "target": 13,
            "weight": 1
        },
        {
            "source": 23,
            "target": 15,
            "weight": 1
        },
        {
            "source": 66,
            "target": 5,
            "weight": 1
        },
        {
            "source": 36,
            "target": 57,
            "weight": 1
        },
        {
            "source": 40,
            "target": 13,
            "weight": 1
        },
        {
            "source": 0,
            "target": 21,
            "weight": 1
        },
        {
            "source": 38,
            "target": 88,
            "weight": 1
        },
        {
            "source": 25,
            "target": 10,
            "weight": 1
        },
        {
            "source": 56,
            "target": 39,
            "weight": 1
        },
        {
            "source": 6,
            "target": 32,
            "weight": 1
        },
        {
            "source": 48,
            "target": 88,
            "weight": 1
        }
    ]
}